{
  "build": {
    "beforeDevCommand": "npm run start",
    "beforeBuildCommand": "npm run build",
    "devPath": "http://localhost:1420",
    "distDir": "../dist/pluto/browser"
  },
  "package": {
    "productName": "pluto",
    "version": "0.0.0"
  },
  "tauri": {
    "allowlist": {
      "all": false,
      "shell": {
        "all": false,
        "open": true
      }
    },
    "windows": [
      {
        "title": "pluto",
        "width": 800,
        "height": 600
      }
    ],
    "security": {
      "csp": null
    },
    "bundle": {
      "active": true,
      "targets": "all",
      "identifier": "com.tauri.dev",
      "icon": [
        "icons/icon.png"
      ]
    }
  }
}
